GTL/GTL_syntax.py
GTL/__init__.py
GTL/cell.py
GTL/cli.py
GTL/glyph.py
GTL/typeface.py
GTL/shape_functions/__init__.py
GTL/shape_functions/_utilities.py
GTL/shape_functions/do_nothing.py
GTL/shape_functions/ellipse.py
GTL/shape_functions/ellipse_quarter.py
GTL/shape_functions/glyph.py
GTL/shape_functions/random_function.py
GTL/shape_functions/rectangle.py
GTL-0.0.1.dist-info/METADATA
GTL-0.0.1.dist-info/WHEEL
GTL-0.0.1.dist-info/entry_points.txt
GTL-0.0.1.dist-info/top_level.txt
GTL-0.0.1.dist-info/RECORD
